
{ "ele" : "545", "tpabr" : "br", "cdabr" : "br", "carper" : "1", "md" : "N", "t" : "2", "f" : "o", "dg" : "30/10/2022", "hg" : "19:05:21", "dt" : "30/10/2022", "ht" : "19:05:10", "dv" : "s", "tf" : "n", "v" : "1", "esae" : "n", "mnae" : "", "s" : "472075", "st" : "413340", "pst" : "87,55", "snt" : "58735", "psnt" : "12,45", "si" : "413293", "psi" : "87,54", "sni" : "47", "psni" : "12,46", "sa" : "413293", "psa" : "100,00", "sna" : "0", "psna" : "0,00", "e" : "156454011", "ea" : "137042918", "pea" : "100,00", "ena" : "0", "pena" : "0,00", "esi" : "137042918", "pesi" : "87,59", "esni" : "657", "pesni" : "100,00", "c" : "108933342", "pc" : "79,48", "a" : "28109576", "pa" : "20,52", "vscv" : "0", "vnom" : "103966039", "pvnom" : "100,00", "vvc" : "103966039", "pvvc" : "95,44", "vb" : "1542546", "pvb" : "1,42", "tvn" : "3424757", "ptvn" : "3,14", "vn" : "3424757", "pvn" : "100,00", "vnt" : "0", "pvnt" : "0,00", "vp" : "0", "pvp" : "0,00", "vv" : "103966039", "pvv" : "100,00", "van" : "0", "pvan" : "0,00", "vansj" : "0", "pvansj" : "0,00", "tv" : "108933342", "cand" : [ 
{ "seq" : "1", "sqcand" : "280001607829", "n" : "13", "nm" : "LULA", "cc" : "PT - Federação Brasil da Esperança - FE BRASIL (PT\/PC do B\/PV) \/ SOLIDARIEDADE \/ Federação PSOL REDE (PSOL\/REDE) \/ PSB \/ AGIR \/ AVANTE \/ PROS", "nv" : "GERALDO ALCKMIN", "e" : "n", "st" : "", "dvt" : "Válido", "vap" : "52481695", "pvap" : "50,48" }, 
{ "seq" : "2", "sqcand" : "280001618036", "n" : "22", "nm" : "JAIR BOLSONARO", "cc" : "PL - PP \/ REPUBLICANOS \/ PL", "nv" : "BRAGA NETTO", "e" : "n", "st" : "", "dvt" : "Válido", "vap" : "51484344", "pvap" : "49,52" } ] }